agent/__init__.py
agent/agent.py
agent/metrics_utils.py
server/__init__.py
server/config_loader.py
server/http_bridge.py
server/server.py
monitoring_system_server_report_test-0.1.2.dist-info/METADATA
monitoring_system_server_report_test-0.1.2.dist-info/WHEEL
monitoring_system_server_report_test-0.1.2.dist-info/entry_points.txt
monitoring_system_server_report_test-0.1.2.dist-info/top_level.txt
monitoring_system_server_report_test-0.1.2.dist-info/RECORD
